mathfunctions.py
setup.py
ajl_mathfunctions.egg-info/PKG-INFO
ajl_mathfunctions.egg-info/SOURCES.txt
ajl_mathfunctions.egg-info/dependency_links.txt
ajl_mathfunctions.egg-info/top_level.txt