Metadata-Version: 1.0
Name: ajl-mathfunctions
Version: 1.0
Summary: testing package that contains two math functions
Home-page: UNKNOWN
Author: Andreas Luttens
Author-email: andreas.luttens@gmail.com
License: UNKNOWN
Platform: UNKNOWN
